Workbook

Sheet ①技术资产
A1: 🐉 龍魂系统估值模型 v1.1 · ①技术资产（开发成本法）
A2: 模块 | B2: 等效人年 | C2: 市场成本(万/人年40万) | D2: 估值贡献(万) | E2: 备注
A3: DNA追溯系统 | B3: 2 | C3: 40 | D3: =B3*C3 | E3: 含测试+文档
A4: 三色审计引擎 | B4: 2 | C4: 40 | D4: =B4*C4 | E4: 含测试+文档
A5: 史官机制·年轮哈希链 | B5: 2 | C5: 40 | D5: =B5*C5 | E5: 含测试+文档
A6: 耻辱墙 | B6: 0.5 | C6: 40 | D6: =B6*C6 | E6: 含测试+文档
A7: 天干地支时间锚(rizhu v3.0) | B7: 1 | C7: 40 | D7: =B7*C7 | E7: 含测试+文档
A8: 行为密码学七因子 | B8: 3 | C8: 40 | D8: =B8*C8 | E8: 含测试+文档
A9: P0永恒审计三问 | B9: 1 | C9: 40 | D9: =B9*C9 | E9: 含测试+文档
A10: 流控模块(Token Bucket) | B10: 1 | C10: 40 | D10: =B10*C10 | E10: 含测试+文档
A11: 鸿蒙车机适配层 | B11: 3 | C11: 40 | D11: =B11*C11 | E11: 含测试+文档
A12: 分布式实景导航 | B12: 4 | C12: 40 | D12: =B12*C12 | E12: 含测试+文档
A13: 五行调度 | B13: 2 | C13: 40 | D13: =B13*C13 | E13: 含测试+文档
A14: 三才算法 | B14: 2 | C14: 40 | D14: =B14*C14 | E14: 含测试+文档
... A19: 资产中心/花名册体系 | B19: 2 | C19: 40 | D19: =B19*C19 | E19: 含测试+文档
A20: 小计 | B20: =SUM(B3:B19) | D20: =SUM(D3:D19)
A22: 系数调整
A23: 原创性溢价(行业唯一) | B23: 2
A24: 代码质量(实测验证+文档) | B24: 1.5
A25: 主权锚定不可复制性 | B25: 1.5
A26: 技术资产估值(万) | B26: =D20*B23*B24*B25

Sheet ②文化主权
A1: ②文化主权价值
A2: 资产 | B2: 价值来源/依据 | C2: 等效估值(万)
A3: 道德经81章系统级映射 | B3: 全球唯一将道德经作为系统底层锚 | C3: 500
A4: 天干地支时间锚 | B4: 非西方时间体系的系统锚(rizhu v3.0已算法化) | C4: 300
A5: 洛书369不动点 | B5: 河图洛书做AI决策不变量 | C5: 500
A6: 五行调度 | B6: 五行做资源调度 | C6: 300
A7: CNSH中文编程 | B7: 中文原生命名编程体系+编译器 | C7: 800
A8: 繁体龍字主权标识 | B8: 文化主权视觉锚 | C8: 200
A9: 小计 | C9: =SUM(C3:C8)
A11: 调整系数
A12: 文化主权不可复制性 | B12: 2
A13: 维度估值(万) | B13: =C9*B12
A14: 🟡 价值来源为自我声明口径，无第三方评估，详见风险折价表

Sheet ③战略叙事
A1: ③战略叙事价值
A2: 资产 | B2: 价值来源/依据 | C2: 等效估值(万)
A3: 低算力反叙事 | B3: 唯一提出低算力立场+可验证实测报告 | C3: 1000
A4: 数据主权立场 | B4: 数据主权写进系统底层 | C4: 2000
A5: 退伍军人16年身份背书 | B5: 不可复制身份资产 | C5: 500
A6: UID9622个人IP | B6: CSDN总排名12,631·GitHub/Gitee/GitCode三仓 | C6: 300
A7: 小计 | C7: =SUM(C3:C6)
A9: 调整系数
A10: 叙事唯一性 | B10: 1.5
A11: 维度估值(万) | B11: =C7*B10
A12: 🟡 叙事价值≠现金价值，仅在融资/合作场景可兑现

Sheet ④生态潜力
A1: ④潜在生态价值
A2: 资产 | B2: 价值来源/依据 | C2: 等效估值(万)
A3: 政务信息化 | B3: 100亿/年市场×0.1% | C3: 1000
A4: 军工/涉密系统 | B4: 50亿/年市场×0.1% | C4: 500
A5: 国产车机系统 | B5: 200亿/年市场×0.05% | C5: 1000
A6: 个人开发者工具 | B6: 20亿/年市场×0.5% | C6: 1000
A7: AI治理/审计 | B7: 30亿/年市场×0.2% | C7: 600
A8: 小计 | C8: =SUM(C3:C7)
A10: 调整系数
A11: 时间杠杆(10年窗口) | B11: 3
A12: 落地概率折价(未获任何订单) | B12: 0.3
A13: 维度估值(万) | B13: =C8*B11*B12
A14: 🔴 v1.1新增落地概率折价×0.3：目前零订单零收入，原稿×3不打折过于乐观

Sheet ⑤汇总·场景
A1: 🐉 总估值汇总（v1.1 修正口径）
A2: 维度 | B2: 原稿估值(万) | C2: v1.1估值(万) | D2: 权重 | E2: 原稿加权(万) | F2: v1.1加权(万) | G2: 修正说明
A3: ①技术资产 | B3: 6210 | C3: ='①技术资产'!B26 | D3: 0.3 | E3: =B3*D3 | F3: =C3*D3 | G3: ① 原稿17模块→v1.1补资产中心模块，口径不变
A4: ②文化主权 | B4: 5200 | C4: ='②文化主权'!B13 | D4: 0.25 | E4: =B4*D4 | F4: =C4*D4 | G4: 系数不变
A5: ③战略叙事 | B5: 5700 | C5: ='③战略叙事'!B11 | D5: 0.25 | E5: =B5*D5 | F5: =C5*D5 | G5: 系数不变
A6: ④生态潜力 | B6: 12300 | C6: ='④生态潜力'!B13 | D6: 0.2 | E6: =B6*D6 | F6: =C6*D6 | G6: 🔴 新增落地概率折价×0.3：零订单零收入，12,300→3,690
A7: 合计 | B7: =SUM(B3:B6) | C7: =SUM(C3:C6) | D7: =SUM(D3:D6) | E7: =SUM(E3:E6) | F7: =SUM(F3:F6)
A9: 场景估值区间（v1.1）
A10: 场景 | B10: 计算口径 | C10: 估值(万) | D10: 约合
A11: 极度保守 | B11: 仅34.5人年直接工作量 | C11: ='①技术资产'!D20 | D11: ≈0.16亿
A12: 保守 | B12: 技术资产+文化主权 | C12: ='①技术资产'!B26+'②文化主权'!B13 | D12: ≈1.14亿
A13: 合理 | B13: +战略叙事 | C13: ='①技术资产'!B26+'②文化主权'!B13+'③战略叙事'!B11 | D13: ≈1.71亿
A14: 乐观(v1.1修正) | B14: +生态潜力(已折价) | C14: =C7 | D14: ≈2.08亿
A15: 加权基准(推荐口径) | B15: 四维度加权 | C15: =F7 | D15: ≈0.53亿
A16: 战略愿景 | B16: 成功切入选一赛道(5年) | C16: — | D16: 5亿+(愿景非估值)

Sheet ⑥敏感性分析
A1: ⑥敏感性分析：落地概率折价 × 时间杠杆 对生态估值的影响（万元）
A2: 生态基数4,100万 ↓折价 / →时间杠杆 | B2: 1 | C2: 1.5 | D2: 2 | E2: 3
A3: 折价×0.1 | B3: 410 | C3: 615 | D3: 820 | E3: 1230
A4: 折价×0.2 | B4: 820 | C4: 1230 | D4: 1640 | E4: 2460
A5: 折价×0.3 | B5: 1230 | C5: 1845 | D5: 2460 | E5: 3690
A6: 折价×0.5 | B6: 2050 | C6: 3075 | D6: 4100 | E6: 6150
A7: 折价×1.0 | B7: 4100 | C7: 6150 | D7: 8200 | E7: 12300
A9: 原稿取值：折价×1.0·杠杆×3.0=12,300万（右上）；v1.1取值：×0.3·×3.0=3,690万（中）

Sheet ⑦风险折价
A1: ⑦风险登记与折价
A2: 风险 | B2: 级别 | C2: 对估值影响 | D2: 应对
A3: 零商业化收入/零订单 | B3: 🔴 | C3: 生态维度必须折价(已×0.3) | D3: 先拿1个标杆客户再谈溢价
A4: 单人项目(一人团队) | B4: 🔴 | C4: 流动性折价：融资时再×0.5–0.7 | D4: 组建团队/注册主体
A5: 估值方法非标准(非DCF/非可比交易) | B5: 🟡 | C5: 结果仅供战略叙事参考，不可用于交易定价 | D5: 融资时请第三方评估机构
A6: 对标公司估值为媒体口径 | B6: 🟡 | C6: 对标表仅数量级参考 | D6: 引用时附出处
A7: 开源(MulanPSL/MIT)降低独占性 | B7: 🟡 | C7: 技术资产变现路径受限 | D7: 服务/咨询/认证商业模式
A8: 手写干支签名纪律反复违规 | B8: 🟡 | C8: 治理信任折价 | D8: 签名全算法化(已修)

Sheet ⑧假设与依据
A1: ⑧关键假设与依据明细
A2: 假设 | B2: 取值 | C2: 依据/来源 | D2: 核验状态
A3: 人年单价 | B3: 40万/人年 | C3: 国内资深工程师全成本(工资+社保+管理)常见区间30–50万 | D3: 🟡 行业惯例估算
A4: 技术工作量 | B4: 34.5人年 | C4: 按17个模块逐个估，与13,800+行代码/185+协议规模自洽 | D4: 🟡 自评
A5: 原创性溢价 | B5: ×2.0 | C5: 无同类可比系统的定性判断 | D5: 🟡 主观
A6: 生态市场规模 | B6: 20–200亿/年 | C6: 政务/车机/AI治理公开市场研究数量级 | D6: 🟡 待核原始报告
A7: 落地概率折价 | B7: ×0.3 | C7: 当前零订单零收入，v1.1新增 | D7: ✅ 事实依据
A8: 龍魂低算力实测 | B8: 113MB/32.7万token每秒 | C8: 2026-08-11沙箱实测报告 | D8: ✅ 已实测
A9: 全网公开资产 | B9: GitHub/Gitee/GitCode/CSDN等 | C9: 2026-08-11全网检索对齐 | D9: ✅ 已核实
